beforerr-2024.11.12.dist-info/METADATA
beforerr-2024.11.12.dist-info/WHEEL
beforerr-2024.11.12.dist-info/entry_points.txt
beforerr-2024.11.12.dist-info/licenses/LICENSE
beforerr/__init__.py
beforerr/_modidx.py
beforerr/basics.py
beforerr/core.py
beforerr/io/__init__.py
beforerr/io/arrow_ipc.py
beforerr/io/json.py
beforerr/io/pickle.py
beforerr/io/polars.py
beforerr/matplotlib/__init__.py
beforerr/matplotlib/styles/publication.mplstyle
beforerr/polars.py
beforerr/project.py
beforerr/r.py
beforerr/tplot.py
beforerr-2024.11.12.dist-info/RECORD
