Metadata-Version: 2.1
Name: beforerr
Version: 2024.11.12
Summary: Personal Python utility library
Author-Email: Beforerr <zzj956959688@gmail.com>
Project-URL: Homepage, https://beforerr.github.io/beforerr_dev
Project-URL: Repository, https://github.com/beforerr/beforerr_dev
Requires-Python: >=3.10
Requires-Dist: pydantic
Requires-Dist: plum-dispatch
Requires-Dist: universal_pathlib
Requires-Dist: intake
Requires-Dist: pipe
Requires-Dist: loguru
Requires-Dist: rich
Provides-Extra: r
Requires-Dist: rpy2; extra == "r"
Requires-Dist: rpy2_arrow; extra == "r"
Provides-Extra: dev
Requires-Dist: nbdev; extra == "dev"
Requires-Dist: ipykernel; extra == "dev"
